{
    "list": [
        {
            "id": 453511,
            "brandName": "uu4CBk7N5f",
            "msBrandId": 454223,
            "msBrandName": "RuY4eMLuQX",
            "producePlace": "KRqhVdzX3p",
            "sellingPoint": "vNJjEOIt1b",
            "description": "QoLxcoTz7w",
            "officialLink": "YNkWT8gvgX",
            "logoAttachmentLink": "S4bScKAUV0",
            "logoAttachmentName": "qOFpQlWYE9",
            "supplierId": 454466,
            "supplierName": "tnem1UI01V",
            "status": 80404,
            "operatorNo": "sjwKhOYCQE",
            "operatorName": "6Ewa8Lszzs",
            "operateTime": 1473547671370,
            "dbCreateTime": {
                "content": "{\"link\":\"www.bai.com\",\"img\":\"http://nos.netease.com/haitao/10cbStkzKbnx1sBmaxresdefault.jpg\"}",
                "isEdit": 1,
                "materialId": 454502,
                "format": "{ \"text\": \"上限15个字\",\"image\": \"960*675\",\"imageUrl\": \"http://nos.netease.com/haitao/SAWdsVtAzqHTem1%E7%B1%BB%E7%9B%AE%E7%A1%AE%E8%AE%A4%E9%A1%B5%E9%9D%A2_03.jpg\"}",
                "templateId": 1
            },
            "dbUpdateTime": {
                "content": "{\"link\":\"www.bai.com\",\"img\":\"http://nos.netease.com/haitao/10cbStkzKbnx1sBmaxresdefault.jpg\"}",
                "isEdit": 1,
                "materialId": 455199,
                "format": "{ \"text\": \"上限15个字\",\"image\": \"960*675\",\"imageUrl\": \"http://nos.netease.com/haitao/SAWdsVtAzqHTem1%E7%B1%BB%E7%9B%AE%E7%A1%AE%E8%AE%A4%E9%A1%B5%E9%9D%A2_03.jpg\"}",
                "templateId": 1
            }
        },
        {
            "id": 455935,
            "brandName": "rln8qV73za",
            "msBrandId": 455984,
            "msBrandName": "0jngonKHm8",
            "producePlace": "dWPXF1HLkD",
            "sellingPoint": "TjXfWsZzeJ",
            "description": "xLS4uStBen",
            "officialLink": "FLMBldswWs",
            "logoAttachmentLink": "gs6C9TdOew",
            "logoAttachmentName": "ZYjztMtVMY",
            "supplierId": 456687,
            "supplierName": "Gk2jbFPAtF",
            "status": 69252,
            "operatorNo": "UB50EhamPX",
            "operatorName": "pb7pd3Tt4n",
            "operateTime": 1473547750951,
            "dbCreateTime": {
                "content": "{\"link\":\"www.bai.com\",\"img\":\"http://nos.netease.com/haitao/10cbStkzKbnx1sBmaxresdefault.jpg\"}",
                "isEdit": 1,
                "materialId": 457010,
                "format": "{ \"text\": \"上限15个字\",\"image\": \"960*675\",\"imageUrl\": \"http://nos.netease.com/haitao/SAWdsVtAzqHTem1%E7%B1%BB%E7%9B%AE%E7%A1%AE%E8%AE%A4%E9%A1%B5%E9%9D%A2_03.jpg\"}",
                "templateId": 1
            },
            "dbUpdateTime": {
                "content": "{\"link\":\"www.bai.com\",\"img\":\"http://nos.netease.com/haitao/10cbStkzKbnx1sBmaxresdefault.jpg\"}",
                "isEdit": 1,
                "materialId": 457940,
                "format": "{ \"text\": \"上限15个字\",\"image\": \"960*675\",\"imageUrl\": \"http://nos.netease.com/haitao/SAWdsVtAzqHTem1%E7%B1%BB%E7%9B%AE%E7%A1%AE%E8%AE%A4%E9%A1%B5%E9%9D%A2_03.jpg\"}",
                "templateId": 1
            }
        },
        {
            "id": 458633,
            "brandName": "9k4DqpDRBa",
            "msBrandId": 459299,
            "msBrandName": "1wKbEKNTXI",
            "producePlace": "2qj93MaPpy",
            "sellingPoint": "UVaEsomKcO",
            "description": "Bw32clsZM2",
            "officialLink": "9IQdK5TDYw",
            "logoAttachmentLink": "NQUXE8xon5",
            "logoAttachmentName": "C9dXYL244D",
            "supplierId": 460028,
            "supplierName": "Bbjnvb7Xq0",
            "status": 76592,
            "operatorNo": "W1TlBWjQlM",
            "operatorName": "ncuHqP7FhM",
            "operateTime": 1473547650180,
            "dbCreateTime": {
                "content": "{\"link\":\"www.bai.com\",\"img\":\"http://nos.netease.com/haitao/10cbStkzKbnx1sBmaxresdefault.jpg\"}",
                "isEdit": 1,
                "materialId": 460417,
                "format": "{ \"text\": \"上限15个字\",\"image\": \"960*675\",\"imageUrl\": \"http://nos.netease.com/haitao/SAWdsVtAzqHTem1%E7%B1%BB%E7%9B%AE%E7%A1%AE%E8%AE%A4%E9%A1%B5%E9%9D%A2_03.jpg\"}",
                "templateId": 1
            },
            "dbUpdateTime": {
                "content": "{\"link\":\"www.bai.com\",\"img\":\"http://nos.netease.com/haitao/10cbStkzKbnx1sBmaxresdefault.jpg\"}",
                "isEdit": 1,
                "materialId": 460844,
                "format": "{ \"text\": \"上限15个字\",\"image\": \"960*675\",\"imageUrl\": \"http://nos.netease.com/haitao/SAWdsVtAzqHTem1%E7%B1%BB%E7%9B%AE%E7%A1%AE%E8%AE%A4%E9%A1%B5%E9%9D%A2_03.jpg\"}",
                "templateId": 1
            }
        }
    ],
    "total": "lfnxBMMMR8"
}